ProxyRipper/ProxyRipper.py
ProxyRipper/__init__.py
ProxyRipper.py-1.0.dist-info/LICENCE
ProxyRipper.py-1.0.dist-info/METADATA
ProxyRipper.py-1.0.dist-info/WHEEL
ProxyRipper.py-1.0.dist-info/top_level.txt
ProxyRipper.py-1.0.dist-info/RECORD
