Metadata-Version: 2.1
Name: ProxyRipper.py
Version: 1.0
Summary: Tool for scrapping valid proxies
Author: Hex24 (Markas Vielavičius)
Author-email: <markas.vielavicius@gmail.com>
Keywords: python,proxy,scrapper,ripper,api,proxies
Classifier: Development Status :: 1 - Planning
Classifier: Intended Audience :: Developers
Classifier: Programming Language :: Python :: 3
Classifier: Operating System :: Unix
Classifier: Operating System :: MacOS :: MacOS X
Classifier: Operating System :: Microsoft :: Windows
License-File: LICENCE
Requires-Dist: requests (==2.25.1)
Requires-Dist: validators (==0.20.0)
